{
    "viotime": {
        "key": "viotime",
        "Path": null
    },
    ":@computed_region_fk4y_hpmh": {
        "key": ":@computed_region_fk4y_hpmh",
        "Path": null
    },
    ":@computed_region_tmcg_v66k": {
        "key": ":@computed_region_tmcg_v66k",
        "Path": null
    },
    ":@computed_region_eziv_p4ck": {
        "key": ":@computed_region_eziv_p4ck",
        "Path": null
    },
    ":@computed_region_urdz_b6n8": {
        "key": ":@computed_region_urdz_b6n8",
        "Path": null
    },
    ":@computed_region_xbxg_7ifr": {
        "key": ":@computed_region_xbxg_7ifr",
        "Path": null
    },
    ":@computed_region_kwzn_pe6v": {
        "key": ":@computed_region_kwzn_pe6v",
        "Path": null
    }
}